sorcha_addons/__init__.py
sorcha_addons/_version.py
sorcha_addons/activity/__init__.py
sorcha_addons/activity/lsst_comet/LICENSE
sorcha_addons/activity/lsst_comet/__init__.py
sorcha_addons/activity/lsst_comet/lsst_comet_activity.py
sorcha_addons/activity/lsst_comet/model.py
sorcha_addons/activity/lsst_comet/phase.py
sorcha_addons/lightcurve/__init__.py
sorcha_addons/lightcurve/sinusoidal/__init__.py
sorcha_addons/lightcurve/sinusoidal/sinusoidal_lightcurve.py
sorcha_addons-1.0.0.dist-info/licenses/LICENSE.txt
sorcha_addons-1.0.0.dist-info/METADATA
sorcha_addons-1.0.0.dist-info/WHEEL
sorcha_addons-1.0.0.dist-info/top_level.txt
sorcha_addons-1.0.0.dist-info/RECORD
