Metadata-Version: 2.4
Name: sorcha_addons
Version: 1.0.0
Author-email: Meg Schwamb <m.schwamb@qub.ac.uk>
Classifier: Development Status :: 4 - Beta
Classifier: Intended Audience :: Developers
Classifier: Intended Audience :: Science/Research
Classifier: Operating System :: OS Independent
Classifier: Programming Language :: Python
License-File: LICENSE.txt
Requires-Dist: pandas
Requires-Dist: numpy
Requires-Dist: sorcha
Requires-Dist: astropy
Requires-Dist: scipy
Requires-Dist: synphot
Provides-Extra: dev
Requires-Dist: pytest; extra == "dev"
Requires-Dist: pytest-cov; extra == "dev"
Requires-Dist: pre-commit; extra == "dev"
Requires-Dist: sphinx; extra == "dev"
Requires-Dist: sphinx-rtd-theme; extra == "dev"
Requires-Dist: sphinx-autoapi; extra == "dev"
Requires-Dist: black; extra == "dev"
Requires-Dist: nbconvert; extra == "dev"
Requires-Dist: nbsphinx; extra == "dev"
Requires-Dist: ipython; extra == "dev"
Requires-Dist: matplotlib; extra == "dev"
Requires-Dist: numpy; extra == "dev"
Dynamic: license-file
